<?xml version="1.0" encoding="utf-8"?>
<Report xmlns="http://schemas.microsoft.com/sqlserver/reporting/2003/10/reportdefinition">
	<PageHeight>11in</PageHeight>
	<PageWidth>8.5in</PageWidth>
	<TopMargin>0.75in</TopMargin>
	<BottomMargin>0.75in</BottomMargin>
	<LeftMargin>0.75in</LeftMargin>
	<RightMargin>0.75in</RightMargin>
	<DataSources>
		<DataSource Name="DataSource1">
			<!--CONNECTION_PROPERTIES-->
		</DataSource>
	</DataSources>
	<DataSets>
		<DataSet Name="DataSet1">
			<Query>
				<DataSourceName>DataSource1</DataSourceName>
				<CommandType>StoredProcedure</CommandType>
				<CommandText><!--SP_NAME--></CommandText>
				<Timeout>300</Timeout>
				<QueryParameters>
					<!--QUERY_PARAMETERS-->
				</QueryParameters>
			</Query>
			<Fields>
				<!--FIELDS-->
			</Fields>
		</DataSet>
	</DataSets>
	<ReportParameters>
		<!--REPORT_PARAMETERS-->
	</ReportParameters>
	<Body>
		<Height>0pt</Height>
		<Style>
			<BackgroundColor>#ffffff</BackgroundColor>
		</Style>
		<ReportItems>
			<Table Name="##TABLE_NAME##">
				<ZIndex>1</ZIndex>
				<DataSetName>DataSet1</DataSetName>
				<Left>0pt</Left>
				<Top>10pt</Top>
				<Height>0pt</Height>
				<Width>0pt</Width>
				<NoRows>No Record Found</NoRows>
				<PageBreakAtEnd>true</PageBreakAtEnd>
				<TableColumns>
					<!--TABLE_COLUMNS-->
				</TableColumns>
				<Style>
					<FontFamily>Calibri, Verdana, Arial, Helvetica</FontFamily>
				</Style>
				<Header>
					<RepeatOnNewPage>true</RepeatOnNewPage>
					<TableRows>
						<TableRow>
							<Height>.35in</Height>
							<TableCells>
								<!--HEADER_CELLS-->
							</TableCells>
						</TableRow>
					</TableRows>
				</Header>
				<Details>
					<TableRows>
						<TableRow>
							<Height>.25in</Height>
							<TableCells>
								<!--DETAILS_CELLS-->
							</TableCells>
						</TableRow>
					</TableRows>
				</Details>
			</Table>
		</ReportItems>
	</Body>
	<PageFooter>
		<Style/>
		<Height>100%</Height>
		<PrintOnFirstPage>true</PrintOnFirstPage>
		<PrintOnLastPage>true</PrintOnLastPage>
	</PageFooter>
	<CodeModules>
		<CodeModule>rdlcodemoduleversion</CodeModule>
	</CodeModules>
</Report>